ap/store/__init__.py
ap/store/__version__.py
ap/store/database.py
ap_store-0.1.3.dist-info/LICENSE
ap_store-0.1.3.dist-info/METADATA
ap_store-0.1.3.dist-info/WHEEL
ap_store-0.1.3.dist-info/entry_points.txt
ap_store-0.1.3.dist-info/top_level.txt
ap_store-0.1.3.dist-info/RECORD
