Metadata-Version: 2.1
Name: ap-store
Version: 0.1.3
Summary: A simple, sqlite3-backed parameter store
Home-page: UNKNOWN
Author: Anna Poulakos
License: MIT License
Requires-Dist: Click (==7.0)
